src/__init__.py
src/cache.py
src/config.py
src/kernel.py
src/mocks.py
src/prelude.py
src/scripts.py
src/server.py
src/tools.py
src/warehouse.py
src/scripts/get_tables_info.py
src/scripts/list_schemas_configured.py
src/scripts/list_schemas_single_db.py
src/scripts/list_tables.py
src/scripts/run_sql.py
src/scripts/session_prelude.py
astro_dwh_mcp-0.1.0.dist-info/METADATA
astro_dwh_mcp-0.1.0.dist-info/WHEEL
astro_dwh_mcp-0.1.0.dist-info/entry_points.txt
astro_dwh_mcp-0.1.0.dist-info/RECORD
